{"cameraMode":{"drawMode":0,"name":"Shaded","section":"Shading Mode"},"sceneLighting":true,"audioPlay":false,"sceneViewState":{"m_AlwaysRefresh":false,"showFog":true,"showSkybox":true,"showFlares":true,"showImageEffects":true,"showParticleSystems":true,"showVisualEffectGraphs":true,"m_FxEnabled":true},"in2DMode":false,"pivot":{"x":346.5393371582031,"y":350.4523010253906,"z":1396.6884765625},"rotation":{"x":0.07603194564580918,"y":-0.20023971796035767,"z":-0.015584610402584076,"w":-0.976681113243103},"size":895.7774047851563,"orthographic":false}